{
  "auto": [
	{
		"conf" :"OVC",
		"winner" : "SIUE"	
	},
	{
		"conf" :"Big South",
		"winner" : "HPU"
	},
	{
		"conf" : "MVC",
		"winner" : "DRAKE"
	},
	{
		"conf": "ASUN",
		"winner" : "LIPS"
	},
	{
		"conf" : "Summit",
		"winner" : "OMAHA"
	},
	{
		"conf" : "Sun Belt",
		"winner" : "TROY"
	},
	{
		"conf" : "SoCon",
		"winner" : "WOF"
	},
	{
		"conf" : "Northeast",
		"winner" : "STFPA"
	},
	{
		"conf" : "Horizon",
		"winner" : "RMU"
	},
	{
		"conf" : "Coastal",
		"winner" : "UNCW"
	},
	{
		"conf" : "WCC",
		"winner" : "GONZ"
	},
	{
		"conf" : "Southland",
		"winner" : "MCNST"
	},
	{
		"conf" : "Patriot",
		"winner" : "AMER"
	},
	{
		"conf" : "Big Sky",
		"winner" : "MONT"
	},
	{
		"conf" : "America East",
		"winner" : "BRYANT"
	},
	{
		"conf" : "MEAC",
		"winner" : "NORFST"
	},
	{
		"conf" : "MW",
		"winner": "CSU"
	},
	{
		"conf" : "Big 12",
		"winner" : "HOU"
	},
	{
		"conf" : "Big East",
		"winner" : "SJU"
	},
	{
		"conf" : "MAAC",
		"winner" : "MSM"
	},
	{
		"conf" : "MAC",
		"winner" : "AKR"
	},
	{
		"conf" : "ACC",
		"winner" : "DUKE"
	},
	{
		"conf" : "C-USA",
		"winner" : "LIB"
	},
	{
		"conf" : "SWAC",
		"winner" : "ALAST"
	},
	{
		"conf" : "Big West",
		"winner" : "UCSD"
	},
	{
		"conf" : "WAC",
		"winner" : "GCU"
	},
	{
		"conf" : "Ivy",
		"winner" : "YALE"
	},
	{
		"conf" : "A-10",
		"winner" : "VCU"
	},
	{
		"conf" : "SEC",
		"winner" : "FLA"
	},
	{
		"conf" : "AAC",
		"winner" : "MEM"
	},
	{
		"conf" : "B1G",
		"winner" : "MICH"
	}
	],
	"atlarge": [
	{
		"team": "AUB"
	},
	{
		"team": "TENN"
	},
	{
		"team": "ALA"
	},
	{
		"team": "MSU"
	},
	{
		"team": "TTU"
	},
	{
		"team": "ISU"
	},
	{
		"team": "UK"
	},
	{
		"team": "WIS"
	},
	{
		"team": "TXAM"
	},
	{
		"team": "PURD"
	},
	{
		"team": "MARY"
	},
	{
		"team": "ZONA"
	},
	{
		"team": "CLEM"
	},
	{
		"team": "ORE"
	},
	{
		"team": "BYU"
	},
	{
		"team": "ILL"
	},
	{
		"team": "MIZ"
	},
	{
		"team": "MISS"
	},
	{
		"team": "UCLA"
	},
	{
		"team": "MARQ"
	},
	{
		"team": "STMARY"
	},
	{
		"team": "KU"
	},
	{
		"team": "LOU"
	},
	{
		"team": "UCONN"
	},
	{
		"team": "MSST"
	},
	{
		"team": "CREIGH"
	},
	{
		"team": "UGA"
	},
	{
		"team": "BU"
	},
	{
		"team": "OKLA"
	},
	{
		"team": "ARK"
	},
	{
		"team": "UNM"
	},
	{
		"team": "VU"
	},
	{
		"team": "USU"
	},
	{
		"team": "TEX"
	},
	{
		"team": "XAV"
	},
	{
		"team": "SDSU"
	},
	{
		"team": "UNC"
	}
	]
}