{
  "games": [
	{
		"gameId" : 1,
		"awayTeam" : "NOVA",
		"homeTeam" : "PROV",
		"favorite" : "NOVA",
		"spread" : 4.5,
		"gameTime" : "2022-02-16T01:00Z",
		"channel": "CBSSN",
		"awayScore" : 89,
		"homeScore" : 84,
		"cover" : "NOVA"
	},
	{
		"gameId" : 2,
		"awayTeam" : "UK",
		"homeTeam" : "TENN",
		"favorite" : "TENN",
		"spread" : 1.5,
		"gameTime" : "2022-02-16T02:00Z",
		"channel": "ESPN",
		"awayScore" : 63,
		"homeScore" : 76,
		"cover" : "TENN"
	},
	{
		"gameId" : 3,
		"awayTeam" : "SETON",
		"homeTeam" : "UCONN",
		"favorite" : "UCONN",
		"spread" : 5.5,
		"gameTime" : "2022-02-17T01:30Z",
		"channel": "CBSSN",
		"awayScore" : 65,
		"homeScore" : 70,
		"cover" : "SETON"
	},
	{
		"gameId" : 4,
		"awayTeam" : "BU",
		"homeTeam" : "TTU",
		"favorite" : "TTU",
		"spread" : 1.5,
		"gameTime" : "2022-02-17T02:00Z",
		"channel": "ESPN2",
		"awayScore" : 73,
		"homeScore" : 83,
		"cover" : "TTU"
	},
	{
		"gameId" : 5,
		"awayTeam" : "TOW",
		"homeTeam" : "UNCW",
		"favorite" : "TOW",
		"spread" : 3.5,
		"gameTime" : "2022-02-17T23:00Z",
		"channel": "CBSSN",
		"awayScore" : 79,
		"homeScore" : 55,
		"cover" : "TOW"
	},
	{
		"gameId" : 6,
		"awayTeam" : "ND",
		"homeTeam" : "WAKE",
		"favorite" : "WAKE",
		"spread" : 5.5,
		"gameTime" : "2022-02-19T18:00Z",
		"channel": "ACCNX / ESPN+",
		"awayScore" : 74,
		"homeScore" : 79,
		"cover" : "ND"
	},
	{
		"gameId" : 7,
		"awayTeam" : "IOWA",
		"homeTeam" : "OSU",
		"favorite" : "OSU",
		"spread" : 5.5,
		"gameTime" : "2022-02-19T19:30Z",
		"channel": "FOX",
		"awayScore" : 75,
		"homeScore" : 62,
		"cover" : "IOWA"
	},
	{
		"gameId" : 8,
		"awayTeam" : "UNT",
		"homeTeam" : "UAB",
		"favorite" : "UAB",
		"spread" : 4.5,
		"gameTime" : "2022-02-19T21:00Z",
		"channel": "STADIUM",
		"awayScore" : 58,
		"homeScore" : 57,
		"cover" : "UNT"
	},
	{
		"gameId" : 9,
		"awayTeam" : "KU",
		"homeTeam" : "WVU",
		"favorite" : "KU",
		"spread" : 4.5,
		"gameTime" : "2022-02-20T01:00Z",
		"channel": "ESPN",
		"active" : true
	},
	{
		"gameId" : 10,
		"awayTeam" : "MEM",
		"homeTeam" : "SMU",
		"favorite" : "SMU",
		"spread" : "-",
		"gameTime" : "2022-02-20T20:00Z",
		"channel": "ESPN",
		"active" : false
	}
  ]
}