{
  "games": [
	{
		"gameId" : 1,
		"awayTeam" : "UK",
		"homeTeam" : "MSU",
		"favorite" : "UK",
		"spread" : 6.5,
		"gameTime" : "2022-11-16T00:00Z",
		"channel" : "ESPN",
		"overtime" : true,
		"numberOfOT" : 2,
		"awayScore" : 77,
		"homeScore" : 86,
		"cover" : "MSU"
    },
    {
		"gameId" : 2,
		"awayTeam" : "DUKE",
		"homeTeam" : "KU",
		"favorite" : "DUKE",
		"spread" : 1.5,
		"gameTime" : "2022-11-16T02:30Z",
		"channel" : "ESPN",
		"awayScore" : 64,
		"homeScore" : 69,
		"cover" : "KU"
    },
    {
		"gameId" : 3,
		"awayTeam" : "IOWA",
		"homeTeam" : "SETON",
		"favorite" : "SETON",
		"spread" : 0,
		"gameTime" : "2022-11-17T00:30Z",
		"channel" : "FS1",
		"active" : true
    },
    {
		"gameId" : 4,
		"awayTeam" : "GONZ",
		"homeTeam" : "TEX",
		"favorite" : "TEX",
		"spread" : 2.5,
		"gameTime" : "2022-11-17T02:30Z",
		"channel" : "ESPN2",
		"active" : true
    },
    {
		"gameId" : 5,
		"awayTeam" : "IND",
		"homeTeam" : "XAV",
		"favorite" : "XAV",
		"spread" : "-",
		"gameTime" : "2022-11-18T23:00Z",
		"channel" : "FS1",
		"active" : false
    },
    {
		"gameId" : 6,
		"awayTeam" : "UVA",
		"homeTeam" : "BU",
		"favorite" : "BU",
		"spread" : "-",
		"gameTime" : "2022-11-19T00:00Z",
		"channel" : "ESPN2",
		"active" : false
    },
    {
		"gameId" : 7,
		"awayTeam" : "ILL",
		"homeTeam" : "UCLA",
		"favorite" : "UCLA",
		"spread" : "-",
		"gameTime" : "2022-11-19T02:30Z",
		"channel" : "ESPNU",
		"active" : false
    },
	{
		"gameId" : 8,
		"awayTeam" : "MARY",
		"homeTeam" : "SLU",
		"favorite" : "SLU",
		"spread" : "-",
		"gameTime" : "2022-11-19T18:00Z",
		"channel" : "ESPNEWS",
		"active" : false
    },
    {
		"gameId" : 9,
		"awayTeam" : "UK",
		"homeTeam" : "GONZ",
		"favorite" : "GONZ",
		"spread" : "-",
		"gameTime" : "2022-11-21T00:30Z",
		"channel" : "ESPN",
		"active" : false
    },
    {
		"gameId" : 10,
		"awayTeam" : "HOU",
		"homeTeam" : "ORE",
		"favorite" : "ORE",
		"spread" : "-",
		"gameTime" : "2022-11-21T02:30Z",
		"channel" : "ESPN",
		"active" : false
    }
  ]
}