{
  "games": [
	{
		"gameId" : 161,
		"homeTeam" : 16,
		"awayTeam" : 18,
		"favorite" : 16,
		"spread" : 2.5,
		"gameTime" : "2020-02-25T00:00Z",
		"channel": "ESPN",
		"homeScore" : 82,
		"awayScore" : 67,
		"cover" : 16
	},
	{
		"gameId" : 162,
		"homeTeam" : 64,
		"awayTeam" : 68,
		"favorite" : 68,
		"spread" : 2.5,
		"gameTime" : "2020-02-26T02:00Z",
		"channel": "ESPN2",
		"homeScore" : 65,
		"awayScore" : 51,
		"cover" : 64
	},
	{
		"gameId" : 163,
		"homeTeam" : 74,
		"awayTeam" : 73,
		"favorite" : 74,
		"spread" : 7.5,
		"gameTime" : "2020-02-27T01:30Z",
		"channel": "FS1",
		"homeScore" : 93,
		"awayScore" : 72,
		"cover" : 74
	},
		{
		"gameId" : 164,
		"homeTeam" : 252,
		"awayTeam" : 244,
		"favorite" : 244,
		"spread" : 5.5,
		"gameTime" : "2020-02-28T03:00Z",
		"channel": "ESPN",
		"homeScore" : 57,
		"awayScore" : 48,
		"cover" : 252
	},
		{
		"gameId" : 165,
		"homeTeam" : 251,
		"awayTeam" : 245,
		"favorite" : 251,
		"spread" : 3.5,
		"gameTime" : "2020-02-28T04:00Z",
		"channel": "PACN",
		"homeScore" : 75,
		"awayScore" : 72,
		"cover" : 245
	},
	{
		"gameId" : 166,
		"homeTeam" : 93,
		"awayTeam" : 101,
		"favorite" : 93,
		"spread" : 3.5,
		"gameTime" : "2020-02-29T17:00Z",
		"channel": "BTN",
		"homeScore" : 77,
		"awayScore" : 68,
		"cover" : 93
	},
	{
		"gameId" : 167,
		"homeTeam" : 271,
		"awayTeam" : 268,
		"favorite" : 271,
		"spread" : 6.5,
		"gameTime" : "2020-02-29T20:45Z",
		"channel": "CBS"
	},
	{
		"gameId" : 168,
		"homeTeam" : 25,
		"awayTeam" : 15,
		"favorite" : 15,
		"spread" : 3.5,
		"gameTime" : "2020-02-29T23:00Z",
		"channel": "ESPN"
	},
	{
		"gameId" : 169,
		"homeTeam" : 4,
		"awayTeam" : 1,
		"favorite" : 4,
		"spread" : "-",
		"gameTime" : "2020-03-01T18:00Z",
		"channel": "ESPN"
	},
	{
		"gameId" : 170,
		"homeTeam" : 250,
		"awayTeam" : 247,
		"favorite" : 247,
		"spread" : "-",
		"gameTime" : "2020-03-01T23:00Z",
		"channel": "ESPNU"
	}
  ]
}