{
  "picks": [
    {
		"userId" : 1,
		"game1" : "OKST",
		"game2" : "MICH",
		"game3" : "DUKE",
		"game4" : "MSU",
		"game5" : "SETON",
		"game6" : "OSU",
		"game7" : "USC",
		"game8" : "DUKE",
		"game9" : "CAMP",
		"game10" : "DRAKE"
    },
    {
		"userId" : 2,
		"game1" : "OKST",
		"game2" : "ILL",
		"game3" : "TECH",
		"game4" : "IND",
		"game5" : "UCONN",
		"game6" : "ILL",
		"game7" : "USC",
		"game8" : "UNC",
		"game9" : "CAMP",
		"game10" : "LOYCHI"
    },
    {
		"userId" : 3,
		"game1" : "OKLA",
		"game2" : "MICH",
		"game3" : "TECH",
		"game4" : "MSU",
		"game5" : "UCONN",
		"game6" : "ILL",
		"game7" : "UCLA",
		"game8" : "DUKE",
		"game9" : "CAMP",
		"game10" : "LOYCHI"
    },
	{
		"userId" : 4,
		"game1" : "OKST",
		"game2" : "ILL",
		"game3" : "DUKE",
		"game4" : "MSU",
		"game5" : "SETON",
		"game6" : "OSU",
		"game7" : "UCLA",
		"game8" : "DUKE",
		"game9" : "WINTH",
		"game10" : "DRAKE"
    },
	{
		"userId" : 5,
		"game1" : "OKST",
		"game2" : "MICH",
		"game3" : "TECH",
		"game4" : "MSU",
		"game5" : "SETON",
		"game6" : "OSU",
		"game7" : "USC",
		"game8" : "UNC",
		"game9" : "WINTH",
		"game10" : "DRAKE"
    },
	{
		"userId" : 6,
		"game1" : "OKST",
		"game2" : "ILL",
		"game3" : "DUKE",
		"game4" : "MSU",
		"game5" : "UCONN",
		"game6" : "",
		"game7" : "",
		"game8" : "",
		"game9" : "",
		"game10" : ""
    },    
	{
		"userId" : 7,
		"game1" : "OKLA",
		"game2" : "MICH",
		"game3" : "DUKE",
		"game4" : "MSU",
		"game5" : "UCONN",
		"game6" : "OSU",
		"game7" : "UCLA",
		"game8" : "UNC",
		"game9" : "CAMP",
		"game10" : "LOYCHI"
    },
	{
		"userId" : 8,
		"game1" : "OKLA",
		"game2" : "MICH",
		"game3" : "DUKE",
		"game4" : "MSU",
		"game5" : "",
		"game6" : "OSU",
		"game7" : "UCLA",
		"game8" : "UNC",
		"game9" : "",
		"game10" : ""
    },
	{
		"userId" : 9,
		"game1" : "OKST",
		"game2" : "ILL",
		"game3" : "TECH",
		"game4" : "MSU",
		"game5" : "UCONN",
		"game6" : "ILL",
		"game7" : "UCLA",
		"game8" : "UNC",
		"game9" : "WINTH",
		"game10" : "LOYCHI"
    },	
	{
		"userId" : 10,
		"game1" : "OKST",
		"game2" : "ILL",
		"game3" : "DUKE",
		"game4" : "MSU",
		"game5" : "SETON",
		"game6" : "OSU",
		"game7" : "UCLA",
		"game8" : "UNC",
		"game9" : "WINTH",
		"game10" : "DRAKE"
    },
	{
		"userId" : 11,
		"game1" : "OKLA",
		"game2" : "ILL",
		"game3" : "DUKE",
		"game4" : "MSU",
		"game5" : "SETON",
		"game6" : "ILL",
		"game7" : "USC",
		"game8" : "UNC",
		"game9" : "CAMP",
		"game10" : "DRAKE"
    },
	{
		"userId" : 12,
		"game1" : "OKST",
		"game2" : "MICH",
		"game3" : "TECH",
		"game4" : "MSU",
		"game5" : "SETON",
		"game6" : "ILL",
		"game7" : "UCLA",
		"game8" : "UNC",
		"game9" : "CAMP",
		"game10" : "LOYCHI"
    },
	{
		"userId" : 13,
		"game1" : "OKLA",
		"game2" : "MICH",
		"game3" : "DUKE",
		"game4" : "MSU",
		"game5" : "UCONN",
		"game6" : "OSU",
		"game7" : "USC",
		"game8" : "UNC",
		"game9" : "WINTH",
		"game10" : "LOYCHI"
    },
	{
		"userId" : 14,
		"game1" : "OKLA",
		"game2" : "",
		"game3" : "",
		"game4" : "",
		"game5" : "",
		"game6" : "",
		"game7" : "",
		"game8" : "",
		"game9" : "",
		"game10" : ""
    },
	{
		"userId" : 15,
		"game1" : "",
		"game2" : "ILL",
		"game3" : "DUKE",
		"game4" : "IND",
		"game5" : "UCONN",
		"game6" : "OSU",
		"game7" : "UCLA",
		"game8" : "DUKE",
		"game9" : "",
		"game10" : ""
    },
	{
		"userId" : 16,
		"game1" : "OKLA",
		"game2" : "MICH",
		"game3" : "TECH",
		"game4" : "IND",
		"game5" : "SETON",
		"game6" : "ILL",
		"game7" : "UCLA",
		"game8" : "DUKE",
		"game9" : "WINTH",
		"game10" : "LOYCHI"
    },
	{
		"userId" : 17,
		"game1" : "OKLA",
		"game2" : "MICH",
		"game3" : "DUKE",
		"game4" : "MSU",
		"game5" : "UCONN",
		"game6" : "OSU",
		"game7" : "UCLA",
		"game8" : "DUKE",
		"game9" : "WINTH",
		"game10" : "LOYCHI"
    },
	{
		"userId" : 18,
		"game1" : "OKLA",
		"game2" : "ILL",
		"game3" : "DUKE",
		"game4" : "MSU",
		"game5" : "SETON",
		"game6" : "ILL",
		"game7" : "USC",
		"game8" : "UNC",
		"game9" : "CAMP",
		"game10" : "LOYCHI"
    },
	{
		"userId" : 19,
		"game1" : "OKST",
		"game2" : "MICH",
		"game3" : "TECH",
		"game4" : "MSU",
		"game5" : "UCONN",
		"game6" : "ILL",
		"game7" : "UCLA",
		"game8" : "DUKE",
		"game9" : "CAMP",
		"game10" : "LOYCHI"
    },
	{
		"userId" : 20,
		"game1" : "OKLA",
		"game2" : "MICH",
		"game3" : "TECH",
		"game4" : "IND",
		"game5" : "SETON",
		"game6" : "ILL",
		"game7" : "USC",
		"game8" : "UNC",
		"game9" : "CAMP",
		"game10" : "LOYCHI"
    },
	{
		"userId" : 21,
		"game1" : "",
		"game2" : "MICH",
		"game3" : "TECH",
		"game4" : "IND",
		"game5" : "UCONN",
		"game6" : "OSU",
		"game7" : "USC",
		"game8" : "UNC",
		"game9" : "WINTH",
		"game10" : "DRAKE"
    },
	{
		"userId" : 22,
		"game1" : "OKST",
		"game2" : "ILL",
		"game3" : "DUKE",
		"game4" : "IND",
		"game5" : "SETON",
		"game6" : "ILL",
		"game7" : "USC",
		"game8" : "UNC",
		"game9" : "CAMP",
		"game10" : "LOYCHI"
    },
	{
		"userId" : 23,
		"game1" : "",
		"game2" : "",
		"game3" : "",
		"game4" : "",
		"game5" : "",
		"game6" : "",
		"game7" : "",
		"game8" : "",
		"game9" : "",
		"game10" : ""
    },
	{
		"userId" : 24,
		"game1" : "OKST",
		"game2" : "ILL",
		"game3" : "DUKE",
		"game4" : "MSU",
		"game5" : "UCONN",
		"game6" : "ILL",
		"game7" : "USC",
		"game8" : "DUKE",
		"game9" : "WINTH",
		"game10" : "LOYCHI"
    },
	{
		"userId" : 25,
		"game1" : "OKST",
		"game2" : "ILL",
		"game3" : "DUKE",
		"game4" : "IND",
		"game5" : "UCONN",
		"game6" : "ILL",
		"game7" : "UCLA",
		"game8" : "UNC",
		"game9" : "WINTH",
		"game10" : "LOYCHI"
    },
	{
		"userId" : 26,
		"game1" : "",
		"game2" : "",
		"game3" : "",
		"game4" : "",
		"game5" : "",
		"game6" : "",
		"game7" : "",
		"game8" : "",
		"game9" : "",
		"game10" : ""
    },
	{
		"userId" : 27,
		"game1" : "OKLA",
		"game2" : "ILL",
		"game3" : "DUKE",
		"game4" : "MSU",
		"game5" : "",
		"game6" : "ILL",
		"game7" : "UCLA",
		"game8" : "DUKE",
		"game9" : "",
		"game10" : ""
    },
	{
		"userId" : 28,
		"game1" : "OKST",
		"game2" : "MICH",
		"game3" : "TECH",
		"game4" : "MSU",
		"game5" : "UCONN",
		"game6" : "OSU",
		"game7" : "UCLA",
		"game8" : "UNC",
		"game9" : "WINTH",
		"game10" : "LOYCHI"
    },
	{
		"userId" : 29,
		"game1" : "OKST",
		"game2" : "ILL",
		"game3" : "DUKE",
		"game4" : "MSU",
		"game5" : "",
		"game6" : "ILL",
		"game7" : "USC",
		"game8" : "UNC",
		"game9" : "WINTH",
		"game10" : "LOYCHI"
    },
	{
		"userId" : 30,
		"game1" : "OKLA",
		"game2" : "",
		"game3" : "",
		"game4" : "",
		"game5" : "",
		"game6" : "",
		"game7" : "",
		"game8" : "",
		"game9" : "",
		"game10" : ""
    },
	{
		"userId" : 31,
		"game1" : "OKLA",
		"game2" : "ILL",
		"game3" : "DUKE",
		"game4" : "MSU",
		"game5" : "SETON",
		"game6" : "ILL",
		"game7" : "UCLA",
		"game8" : "UNC",
		"game9" : "CAMP",
		"game10" : "LOYCHI"
    }
	]
}